{
  "snapshots": [
    {
      "timestamp": "2025-08-19T14:48:22.820Z",
      "date": "Tue Aug 19 2025",
      "metrics": {
        "overallScore": 82,
        "missingRoutes": 232,
        "infrastructureIntegration": {
          "websocket": 60,
          "notifications": 50,
          "themes": 65,
          "i18n": 75,
          "auth": 80
        },
        "deadModules": 0,
        "routesImplemented": 42,
        "integrationImprovements": [
          "WebSocket real-time dashboard updates",
          "Theme toggle integration",
          "i18n multilingual support",
          "Auth-aware UI components",
          "Enhanced notification system"
        ]
      },
      "phase": "Phase 1: Critical Route Implementation"
    },
    {
      "timestamp": "2025-08-19T14:49:41.895Z",
      "date": "Tue Aug 19 2025",
      "metrics": {
        "overallScore": 82,
        "missingRoutes": 232,
        "infrastructureIntegration": {
          "websocket": 60,
          "notifications": 50,
          "themes": 65,
          "i18n": 75,
          "auth": 80
        },
        "deadModules": 0,
        "routesImplemented": 42,
        "integrationImprovements": [
          "WebSocket real-time dashboard updates",
          "Theme toggle integration",
          "i18n multilingual support",
          "Auth-aware UI components",
          "Enhanced notification system"
        ]
      },
      "phase": "Phase 1: Critical Route Implementation"
    }
  ],
  "baseline": {
    "timestamp": "2025-08-19T14:48:22.820Z",
    "date": "Tue Aug 19 2025",
    "metrics": {
      "overallScore": 82,
      "missingRoutes": 232,
      "infrastructureIntegration": {
        "websocket": 60,
        "notifications": 50,
        "themes": 65,
        "i18n": 75,
        "auth": 80
      },
      "deadModules": 0,
      "routesImplemented": 42,
      "integrationImprovements": [
        "WebSocket real-time dashboard updates",
        "Theme toggle integration",
        "i18n multilingual support",
        "Auth-aware UI components",
        "Enhanced notification system"
      ]
    },
    "phase": "Phase 1: Critical Route Implementation"
  }
}